infrapilot_cli/__init__.py
infrapilot_cli/__main__.py
infrapilot_cli/main.py
infrapilot_cli/auth/__init__.py
infrapilot_cli/auth/integration/aws_auth.py
infrapilot_cli/auth/integration/exceptions.py
infrapilot_cli/auth/integration/github_auth.py
infrapilot_cli/auth/integration/manager.py
infrapilot_cli/auth/user/callback_server.py
infrapilot_cli/auth/user/flow.py
infrapilot_cli/auth/user/logout.py
infrapilot_cli/auth/user/pkce.py
infrapilot_cli/auth/user/refresh.py
infrapilot_cli/auth/user/settings.py
infrapilot_cli/auth/user/token_exchange.py
infrapilot_cli/backend/__init__.py
infrapilot_cli/backend/client.py
infrapilot_cli/config/__init__.py
infrapilot_cli/config/token_store.py
infrapilot_cli/core/http_logging.py
infrapilot_cli/core/logging.py
infrapilot_cli/core/modes.py
infrapilot_cli/core/paths.py
infrapilot_cli/core/utils.py
infrapilot_cli/database/__init__.py
infrapilot_cli/database/database.py
infrapilot_cli/database/store.py
infrapilot_cli/discovery/aws.py
infrapilot_cli/dist/index.html
infrapilot_cli/dist/vite.svg
infrapilot_cli/dist/assets/index-Czb8m0vV.css
infrapilot_cli/dist/assets/index-DNFIT3Vd.js
infrapilot_cli/infra/__init__.py
infrapilot_cli/infra/sandbox/__init__.py
infrapilot_cli/infra/sandbox/temp_workspace.py
infrapilot_cli/schema/__init__.py
infrapilot_cli/schema/auth.py
infrapilot_cli/service/devops_probe.py
infrapilot_cli/service/devops_sandbox_runner.py
infrapilot_cli/service/execution_agent.py
infrapilot_cli/service/local_probe.py
infrapilot_cli/service/registry_check.py
infrapilot_cli/ui/banner.py
infrapilot_cli/ui/chat_ui.py
infrapilot_cli/ui/command_registry.py
infrapilot_cli/ui/devops_ui.py
infrapilot_cli/ui/dialog_utils.py
infrapilot_cli/ui/llm_state.py
infrapilot_cli/ui/plan_preview.py
infrapilot_cli/ui/repl.py
infrapilot_cli/ui/theme.py
infrapilot_cli/ui/thread_ui.py
infrapilot_cli/ui/workspace_ui.py
infrapilot_cli/utils/__init__.py
infrapilot_cli/utils/names.py
infrapilot-0.1.1.dist-info/METADATA
infrapilot-0.1.1.dist-info/WHEEL
infrapilot-0.1.1.dist-info/entry_points.txt
infrapilot-0.1.1.dist-info/top_level.txt
infrapilot-0.1.1.dist-info/RECORD
