Metadata-Version: 2.4
Name: infrapilot
Version: 0.1.1
Summary: InfraPilot CLI
Requires-Python: >=3.13
Requires-Dist: keyring>=25.6.0
Requires-Dist: prompt-toolkit>=3.0.52
Requires-Dist: requests>=2.32.5
Requires-Dist: rich>=14.2.0
Requires-Dist: sqlmodel>=0.0.27
Requires-Dist: structlog>=25.5.0
Requires-Dist: starlette>=0.38.0
Requires-Dist: fastapi>=0.121.0
Requires-Dist: uvicorn>=0.38.0
Requires-Dist: sqlalchemy>=2.0.44
Requires-Dist: boto3>=1.41.5
Requires-Dist: botocore>=1.41.5
